Metadata-Version: 2.1
Name: core-module-fancy-tree-registry-app
Version: 2.19.0
Summary: Fancy Tree module for the parser core project
Home-page: https://github.com/usnistgov/core_module_fancy_tree_registry_app
Author: NIST IT Lab
Author-email: itl_inquiries@nist.gov
License-File: LICENSE.md
